sxl/__init__.py
sxl/sxl.py
sxl-0.0.1a10.dist-info/LICENSE.txt
sxl-0.0.1a10.dist-info/METADATA
sxl-0.0.1a10.dist-info/WHEEL
sxl-0.0.1a10.dist-info/top_level.txt
sxl-0.0.1a10.dist-info/RECORD
