Metadata-Version: 1.1
Name: sxl
Version: 0.0.1a10
Summary: A python module to deal with (very) big Excel files.
Home-page: https://github.com/ktr/sxl
Author: Kevin Ryan
Author-email: ktr@26ocb.com
License: MIT
Keywords: data excel xlsx
Platform: UNKNOWN
Classifier: Development Status :: 3 - Alpha
Classifier: Intended Audience :: Developers
Classifier: Topic :: Software Development :: Build Tools
Classifier: Topic :: Office/Business
Classifier: Topic :: Software Development :: Libraries
Classifier: License :: OSI Approved :: MIT License
Classifier: Programming Language :: Python :: 3.4
Classifier: Programming Language :: Python :: 3.5
Classifier: Programming Language :: Python :: 3.6
Classifier: Programming Language :: Python :: 3.7
